solai/__init__.py
solai/app.py
solai-0.1.0.dist-info/LICENSE
solai-0.1.0.dist-info/METADATA
solai-0.1.0.dist-info/WHEEL
solai-0.1.0.dist-info/entry_points.txt
solai-0.1.0.dist-info/top_level.txt
solai-0.1.0.dist-info/RECORD
